scriptchat/__init__.py
scriptchat/__main__.py
scriptchat/core/__init__.py
scriptchat/core/anthropic_client.py
scriptchat/core/commands.py
scriptchat/core/config.py
scriptchat/core/conversations.py
scriptchat/core/exports.py
scriptchat/core/model_defaults.py
scriptchat/core/model_defaults_extra.py
scriptchat/core/ollama_client.py
scriptchat/core/openai_client.py
scriptchat/core/provider_dispatcher.py
scriptchat/ui/__init__.py
scriptchat/ui/app.py
scriptchat/ui/command_handlers.py
scriptchat/ui/selection_menu.py
scriptchat-0.3.0.dist-info/licenses/LICENSE
scriptchat-0.3.0.dist-info/licenses/NOTICE
scriptchat-0.3.0.dist-info/METADATA
scriptchat-0.3.0.dist-info/WHEEL
scriptchat-0.3.0.dist-info/entry_points.txt
scriptchat-0.3.0.dist-info/top_level.txt
scriptchat-0.3.0.dist-info/RECORD
