Metadata-Version: 2.4
Name: scriptchat
Version: 0.3.0
Summary: A terminal-based, scriptable chat client for LLMs (Ollama, OpenAI, Anthropic)
Author: ScriptChat contributors
License:                                  Apache License
Project-URL: Homepage, https://github.com/quasientio/scriptchat
Project-URL: Repository, https://github.com/quasientio/scriptchat
Project-URL: Issues, https://github.com/quasientio/scriptchat/issues
Keywords: llm,chat,cli,ollama,openai,anthropic,terminal
Classifier: Development Status :: 4 - Beta
Classifier: Environment :: Console
Classifier: Framework :: Pytest
Classifier: Intended Audience :: Developers
Classifier: Intended Audience :: End Users/Desktop
Classifier: License :: OSI Approved :: Apache Software License
Classifier: Operating System :: OS Independent
Classifier: Programming Language :: Python :: 3
Classifier: Programming Language :: Python :: 3.10
Classifier: Programming Language :: Python :: 3.11
Classifier: Programming Language :: Python :: 3.12
Classifier: Programming Language :: Python :: 3.13
Classifier: Topic :: Communications :: Chat
Classifier: Topic :: Scientific/Engineering :: Artificial Intelligence
Classifier: Typing :: Typed
Requires-Python: >=3.10
License-File: LICENSE
License-File: NOTICE
Requires-Dist: prompt_toolkit>=3.0.0
Requires-Dist: Pygments>=2.0.0
Requires-Dist: requests>=2.25.0
Requires-Dist: toml>=0.10.0
Provides-Extra: dev
Requires-Dist: pytest>=7.0.0; extra == "dev"
Requires-Dist: pytest-cov>=4.0.0; extra == "dev"
Requires-Dist: coverage>=7.0.0; extra == "dev"
Dynamic: license-file
